jabs/__init__.py
jabs/__main__.py
jabs/behavior_search/__init__.py
jabs/behavior_search/behavior_search_util.py
jabs/classifier/__init__.py
jabs/classifier/classifier.py
jabs/constants.py
jabs/feature_extraction/__init__.py
jabs/feature_extraction/angle_index.py
jabs/feature_extraction/base_features/__init__.py
jabs/feature_extraction/base_features/angles.py
jabs/feature_extraction/base_features/angular_velocity.py
jabs/feature_extraction/base_features/base_group.py
jabs/feature_extraction/base_features/centroid_velocity.py
jabs/feature_extraction/base_features/pairwise_distances.py
jabs/feature_extraction/base_features/point_speeds.py
jabs/feature_extraction/base_features/point_velocities.py
jabs/feature_extraction/feature_base_class.py
jabs/feature_extraction/feature_group_base_class.py
jabs/feature_extraction/features.py
jabs/feature_extraction/landmark_features/__init__.py
jabs/feature_extraction/landmark_features/corner.py
jabs/feature_extraction/landmark_features/food_hopper.py
jabs/feature_extraction/landmark_features/landmark_group.py
jabs/feature_extraction/landmark_features/lixit.py
jabs/feature_extraction/segmentation_features/__init__.py
jabs/feature_extraction/segmentation_features/hu_moments.py
jabs/feature_extraction/segmentation_features/moment_cache.py
jabs/feature_extraction/segmentation_features/moments.py
jabs/feature_extraction/segmentation_features/segment_group.py
jabs/feature_extraction/segmentation_features/shape_descriptors.py
jabs/feature_extraction/social_features/__init__.py
jabs/feature_extraction/social_features/closest_distances.py
jabs/feature_extraction/social_features/closest_fov_angles.py
jabs/feature_extraction/social_features/closest_fov_distances.py
jabs/feature_extraction/social_features/pairwise_social_distances.py
jabs/feature_extraction/social_features/social_distance.py
jabs/feature_extraction/social_features/social_group.py
jabs/feature_extraction/window_operations/__init__.py
jabs_behavior_classifier-0.39.0.dist-info/WHEEL
jabs_behavior_classifier-0.39.0.dist-info/entry_points.txt
jabs_behavior_classifier-0.39.0.dist-info/METADATA
jabs_behavior_classifier-0.39.0.dist-info/RECORD
