Metadata-Version: 2.3
Name: jabs-behavior-classifier
Version: 0.39.0
Summary: 
Author: Glen Beane, Brian Geuther, Keith Sheppard
License: Proprietary
Requires-Dist: h5py>=3.10.0,<4.0.0
Requires-Dist: markdown2>=2.5.1,<3.0.0
Requires-Dist: numpy>=2.0.0,<3.0.0
Requires-Dist: opencv-python-headless>=4.8.1.78,<5.0.0
Requires-Dist: pandas>=2.2.2,<3.0.0
Requires-Dist: pyside6>=6.8.0,!=6.9.0
Requires-Dist: scikit-learn>=1.5.0,<2.0.0
Requires-Dist: shapely>=2.0.1,<3.0.0
Requires-Dist: tabulate>=0.9.0,<1.0.0
Requires-Dist: toml>=0.10.2,<0.11.0
Requires-Dist: xgboost>=2.0.0,<3.0.0
Requires-Dist: pyarrow>=20.0.0,<23.0.0
Requires-Dist: rich>=14.0.0,<15.0.0
Requires-Dist: rich-argparse>=1.7.1,<2.0.0
Requires-Dist: intervaltree>=3.1.0,<4.0.0
Requires-Dist: qt-material-icons>=0.2.0,<0.3.0
Requires-Dist: jsonschema>=4.25.1,<5.0.0
Requires-Dist: click>=8.2.1
Requires-Dist: argparse-formatter>=1.4
Requires-Dist: distinctipy>=1.3.4
Requires-Python: >=3.10, <3.15
Project-URL: Issues, https://github.com/KumarLabJax/JABS-behavior-classifier/issues
Project-URL: Repository, https://github.com/KumarLabJax/JABS-behavior-classifier
